LICENSE.txt
MANIFEST.in
OrderEvents.MD
README.md
requirements.txt
setup.cfg
setup.py
buttonwood/__init__.py
buttonwood.egg-info/PKG-INFO
buttonwood.egg-info/SOURCES.txt
buttonwood.egg-info/dependency_links.txt
buttonwood.egg-info/top_level.txt
buttonwood/MarketMetrics/MicroPrice.py
buttonwood/MarketMetrics/__init__.py
buttonwood/MarketMetrics/EventListeners/MatchSeriesTracker.py
buttonwood/MarketMetrics/EventListeners/OrderEventCountListener.py
buttonwood/MarketMetrics/EventListeners/VolumeTrackingListener.py
buttonwood/MarketMetrics/EventListeners/__init__.py
buttonwood/MarketMetrics/OrderLevelBookListeners/AggressiveImpactListener.py
buttonwood/MarketMetrics/OrderLevelBookListeners/CrossedBookListener.py
buttonwood/MarketMetrics/OrderLevelBookListeners/LastTimeTOBListener.py
buttonwood/MarketMetrics/OrderLevelBookListeners/MarketOrderTicksFromCrossingListener.py
buttonwood/MarketMetrics/OrderLevelBookListeners/PeriodBarListeners.py
buttonwood/MarketMetrics/OrderLevelBookListeners/PriorityListeners.py
buttonwood/MarketMetrics/OrderLevelBookListeners/TimeAtLevelListeners.py
buttonwood/MarketMetrics/OrderLevelBookListeners/TopOfBookSnapshotListeners.py
buttonwood/MarketMetrics/OrderLevelBookListeners/__init__.py
buttonwood/MarketObjects/CancelReasons.py
buttonwood/MarketObjects/Endpoint.py
buttonwood/MarketObjects/Market.py
buttonwood/MarketObjects/MatchSeries.py
buttonwood/MarketObjects/OHLCV.py
buttonwood/MarketObjects/Price.py
buttonwood/MarketObjects/PriceLevel.py
buttonwood/MarketObjects/Product.py
buttonwood/MarketObjects/Quote.py
buttonwood/MarketObjects/RejectReasons.py
buttonwood/MarketObjects/Side.py
buttonwood/MarketObjects/TwoSidedQuote.py
buttonwood/MarketObjects/__init__.py
buttonwood/MarketObjects/EventListeners/OrderEventListener.py
buttonwood/MarketObjects/EventListeners/__init__.py
buttonwood/MarketObjects/Events/BasicEvents.py
buttonwood/MarketObjects/Events/EventChains.py
buttonwood/MarketObjects/Events/EventHandler.py
buttonwood/MarketObjects/Events/OrderEventConstants.py
buttonwood/MarketObjects/Events/OrderEvents.py
buttonwood/MarketObjects/Events/__init__.py
