Metadata-Version: 1.1
Name: buttonwood
Version: 2.0.2
Summary: Buttonwood is a python software package created to help quickly create, (re)build, or analyze markets, market structures, and market participants.
Home-page: https://github.com/nabicht/Buttonwood
Author: Peter F. Nabicht
Author-email: nabicht@gmail.com
License: MIT
Download-URL: https://github.com/nabicht/Buttonwood/archive/v2.0.2.tar.gz
Keywords: markets,finance,electronic markets,microstructure,market analysis
Platform: UNKNOWN
Classifier: Development Status :: 5 - Production/Stable
Classifier: Intended Audience :: Developers
Classifier: Topic :: Office/Business :: Financial
Classifier: License :: OSI Approved :: MIT License
Classifier: Programming Language :: Python :: 3
Classifier: Programming Language :: Python :: 3.6
Classifier: Programming Language :: Python :: 3.7
